marimo_scipy_utils/__init__.py
marimo_scipy_utils/exceptions.py
marimo_scipy_utils/marimo_components.py
marimo_scipy_utils/py.typed
marimo_scipy_utils-0.1.2.dist-info/licenses/LICENSE.txt
marimo_scipy_utils-0.1.2.dist-info/METADATA
marimo_scipy_utils-0.1.2.dist-info/WHEEL
marimo_scipy_utils-0.1.2.dist-info/top_level.txt
marimo_scipy_utils-0.1.2.dist-info/RECORD
