Metadata-Version: 2.4
Name: marimo-scipy-utils
Version: 0.1.2
Summary: A collection of utilities to make it easier to interact with scipy in a marimo notebook, e.g. manipulate distributions, visualize data, etc.
Author-email: Harold Martin <Harold.Martin@gmail.com>
License-Expression: Apache-2.0
Keywords: scipy,matplotlib,marimo,distributions,statistics,visualization,data analysis,data visualization
Classifier: Development Status :: 4 - Beta
Classifier: Intended Audience :: End Users/Desktop
Classifier: Intended Audience :: Science/Research
Classifier: Programming Language :: Python :: 3.11
Classifier: Programming Language :: Python :: 3.12
Classifier: Programming Language :: Python :: 3.13
Requires-Python: >=3.11
License-File: LICENSE.txt
Requires-Dist: marimo
Requires-Dist: matplotlib>=3.8.4
Requires-Dist: scipy>=1.14.1
Dynamic: license-file
